diggercli/__init__.py
diggercli/_version.py
diggercli/api.py
diggercli/auth.py
diggercli/constants.py
diggercli/dg.py
diggercli/diggerconfig.py
diggercli/exceptions.py
diggercli/fileio.py
diggercli/projects.py
diggercli/server.py
diggercli/transformers.py
diggercli/validators.py
diggercli/utils/__init__.py
diggercli/utils/pprint.py
Digger_CLI-1.0.dist-info/LICENSE.txt
Digger_CLI-1.0.dist-info/METADATA
Digger_CLI-1.0.dist-info/WHEEL
Digger_CLI-1.0.dist-info/entry_points.txt
Digger_CLI-1.0.dist-info/top_level.txt
Digger_CLI-1.0.dist-info/RECORD
